cleantext/__init__.py
cleantext/cleantext.py
cleantext-1.1.2.dist-info/LICENSE.txt
cleantext-1.1.2.dist-info/METADATA
cleantext-1.1.2.dist-info/WHEEL
cleantext-1.1.2.dist-info/top_level.txt
cleantext-1.1.2.dist-info/RECORD
