Metadata-Version: 2.1
Name: cleantext
Version: 1.1.2
Summary: An open-source python package to clean raw text data
Home-page: https://github.com/prasanthg3/cleantext
Author: Prasanth Gudiwada
Author-email: prasanth.gudiwada@gmail.com
License: MIT
Platform: UNKNOWN
Requires-Dist: nltk
